{
    "contents": [
        {
            "selector": "github-code-reviews",
            "title": "Code reviews using GitHub",
            "subTitle": "Learn how to submit code to GitHub in a reviewer-friendly way.",
            "routerLink": "/articles/github-code-reviews",
            "imageUrl": "https://i.imgur.com/40SiyIE.jpg"
        },
        {
            "selector": "automation-with-scripts",
            "title": "Scripts for productivity",
            "subTitle": "On benefits of automation of everyday tasks.",
            "routerLink": "/articles/automation-with-scripts",
            "imageUrl": "https://i.imgur.com/MMvnzKH.jpg"
        }
    ]
}